{
    "id": 1784872823,
    "date": "2026-07-24",
    "title": "UK maritime ETS countdown begins",
    "summary": "The UK Emissions Trading Scheme (ETS) will extend to maritime from July 1, 2026, imposing a company-level carbon compliance regime on domestic cargo and passenger vessels over 5,000 GT. Operators must now develop a single Emissions Monitoring Plan (EMP) for their entire fleet, a process managed through the UK METS platform and ETS Registry. This new layer of bureaucracy demands preparation, but the critical question remains: will it genuinely penalize excessive carbon intensity and HFO usage, or merely create more paperwork for the dirtiest ships?",
    "content": "The UK\u2019s decision to extend its Emissions Trading Scheme (UK ETS) to maritime transport from July 1, 2026 marks a significant shift in the regulatory landscape for shipping, introducing a company-level carbon compliance regime that operators must begin preparing for now.\n\nIn the latest edition of DNV\u2019s Maritime Impact podcast, Eirik Nyhus, director, environment for maritime at class society DNV, outlined the practical implications of the new framework, highlighting both the compliance requirements and the outstanding uncertainties that remain ahead of implementation.\n\n\u201cThis is more than just another reporting obligation,\u201d Nyhus said.\n\n\u201cFor operators in scope, the UK ETS introduces a company-level compliance regime with new requirements for emission monitoring, reporting, verification and ultimately the surrender of allowances.\u201d\n\nThe new rules will initially apply to cargo and passenger vessels of 5,000 gross tonnage and above operating on domestic UK voyages. Offshore vessels will be brought into scope later, from January 1, 2027. While the legal framework has now been established, maritime companies face a relatively short timeframe to ensure systems, procedures and reporting structures are ready.\n\nA key feature of the UK approach is the requirement for operators to establish an approved Emissions Monitoring Plan (EMP). Unlike the EU ETS, which relies on vessel-specific documentation, the UK framework adopts a company-wide model. Operators must submit a single EMP covering all vessels under their responsibility, detailing monitoring methodologies, emission sources and calculation approaches.\n\nNyhus explained that approval for an EMP can be sought at any time but no later than 42 days after a company undertakes a maritime activity falling within the scope of the scheme. The process will be managed through the UK\u2019s digital Maritime Emissions Trading Scheme (METS) platform and the UK ETS Registry.\n\nThe introduction of the UK ETS maritime regime also coincides with the end of the previous UK Monitoring, Reporting and Verification (MRV) framework. That system was revoked on April 3, 2026, with residual reporting obligations being absorbed into the new ETS structure from July 1.\n\n\u201cThis means there are no reporting obligations for the period April 3 to June 30,\u201d Nyhus noted, describing the shift as a move into \u201ca new architecture for emissions compliance\u201d.\n\nOperational impacts\n\nAlthough the scope of the scheme is relatively narrow, its impact on operational planning could be substantial. The UK ETS will cover emissions generated on domestic voyages between UK ports, including voyages that begin and end at the same UK port. Importantly, emissions generated during port calls are also covered.\n\n\u201cOne practical consequence is that emissions from port stays on international routes are also captured under the UK ETS,\u201d Nyhus said. \u201cSo even where the voyage itself may be outside the scope, the port call in the UK will still create a surrender obligation for those in-port emissions, as long as the ship itself is in scope.\u201d\n\nThe framework also includes several route-specific provisions. Voyages between Northern Ireland and Great Britain will carry a 50% surrender obligation for voyage emissions, while port stays in both locations remain subject to a full 100% surrender requirement. Meanwhile, voyages between the UK and ports outside the European Economic Area, including UK Overseas Territories and Crown Dependencies, are excluded because they are not treated as domestic voyages.\n\nLike the EU ETS, the UK system covers carbon dioxide, methane and nitrous oxide emissions from combustion processes, as well as methane slip calculated using a tank-to-wake methodology. Methane and nitrous oxide will be reported using IPCC AR5 global warming potentials, ensuring broad alignment with European carbon accounting methods.\n\nHowever, while the emissions scope closely mirrors that of the EU ETS, the implementation architecture differs in several noteworthy respects, Nyhus said.\n\nUnder the UK system, EMPs are submitted directly to regulators instead of undergoing pre-assessment by an accredited verifier. Verification instead focuses on the Annual Emissions Report (AER), which must be submitted by March 31 each year and independently verified by a UK Accreditation Service-accredited verifier.\n\nOperators must then surrender allowances corresponding to verified emissions by April 30 annually. For the inaugural compliance period, reporting will cover only emissions generated between July 1 and December 31, 2026. The associated surrender deadline will fall on April 30, 2028, combined with surrender obligations for emissions generated during 2027.\n\nResponsibility for compliance rests primarily with the registered owner of a vessel. Nevertheless, this responsibility can be transferred to the International Safety Management (ISM) company where a legally binding agreement exists. In such cases, details of the arrangement must be entered into the METS system, Nyhus explained.\n\nAnother departure from the EU model is the absence of an onboard Document of Compliance.\n\n\u201cUnlike the EU ETS, the UK ETS does not require a Document of Compliance to be carried on board,\u201d Nyhus explained. \u201cInstead, compliance is handled digitally through METS and the UK ETS Trading Registry.\u201d\n\nUnanswered questions\n\nDespite the framework now being operational, several important questions remain unanswered. Nyhus identified fuel eligibility, emissions reduction claims and certification requirements as areas where greater regulatory clarity is still needed.\n\n\u201cThe challenge is operationalisation \u2013 in other words, translating legal text into clear, consistent, workable rules for real ships, real voyages and real reporting systems,\u201d he said.\n\nCurrent uncertainties include which fuels qualify when regulations are silent, whether lists contained in Annex A should be interpreted as exhaustive, and how the UK authorities intend to recognise voluntary certification schemes in future. Additional questions surround the relationship between the UK ETS and sustainability criteria under the EU Renewable Energy Directive (RED).\n\nAccording to Nyhus, these issues have practical significance because they influence not only fuel eligibility but also the evidence operators must retain and the methodologies verifiers are expected to apply.\n\nProof requirements also remain under discussion. Industry participants continue to seek clarification regarding acceptable forms of evidence, including whether Proofs of Sustainability, Proofs of Compliance or supplier declarations will be recognised, and whether copies of documentation are sufficient.\n\nFurther complexity may emerge from future political developments. Both the UK and EU have previously indicated an intention to align their respective emissions trading systems, although implementation timelines remain uncertain.\n\n\u201cNegotiations have started, but look to be taking a while, and my guess is that the likely earliest practical year for alignment to happen would be 2028,\u201d Nyhus said. \u201cWhat practical changes this will lead to remains to be seen.\u201d\n\nFor shipowners operating across both UK and European trades, the result is an increasingly complex compliance environment. While the UK and EU regimes share common principles, they differ sufficiently in structure and execution to require dedicated management processes.\n\n\u201cThe UK ETS maritime extension is important not only because it adds a new compliance obligation, but because it reflects the continued development of regional market-based measures in shipping,\u201d Nyhus observed. Operators, he added, are now \u201cincreasingly navigating overlapping carbon frameworks with different boundaries, timelines, tools and evidentiary requirements.\u201d",
    "source_url": "https://www.hellenicshippingnews.com/uk-maritime-ets-countdown-begins/",
    "source": "hellenicshippingnews.com",
    "score": 125,
    "top_image": "https://www.hellenicshippingnews.com/wp-content/uploads/2026/07/22072026.jpg"
}